v2a.py
vocably2anki-0.1.4.dist-info/METADATA
vocably2anki-0.1.4.dist-info/WHEEL
vocably2anki-0.1.4.dist-info/entry_points.txt
vocably2anki-0.1.4.dist-info/top_level.txt
vocably2anki-0.1.4.dist-info/RECORD
