Metadata-Version: 2.4
Name: vocably2anki
Version: 0.1.4
Summary: Converts an exported vocably deck to a simpler format suitable for Anki import
Project-URL: source, https://github.com/gravenimage/vocably2anki
Requires-Python: >=3.12
Requires-Dist: arguably>=1.3.0
